{
  "item-states": [
    {
      "folded": false,
      "id": "febhuGTTFJybsr1A6sjyjK"
    },
    {
      "folded": false,
      "id": "f28I0fsfNPG4obOTCjcpyF"
    },
    {
      "folded": false,
      "id": "f3PmCmtu9A9otFhyUXJrq1"
    },
    {
      "folded": false,
      "id": "3agpzpvftFS5ZDbcj97cR2"
    },
    {
      "folded": false,
      "id": "02yourvWBKTolDhiWRFUOA"
    },
    {
      "folded": false,
      "id": "58DtO/iOxF+JBqDB34HmJ1"
    },
    {
      "folded": false,
      "id": "54nqW1hEpMy77Mu1Amdr+m"
    },
    {
      "folded": false,
      "id": "99Dx+7UFtEmburxSGFx5LI"
    },
    {
      "folded": false,
      "id": "1d23iaUmBL56U4pBlBlV5B"
    },
    {
      "folded": false,
      "id": "8aXxyweJBHF5+StDX6+Kl9"
    },
    {
      "folded": false,
      "id": "76HXkKiMFF5pHHWV6zTiBi"
    },
    {
      "folded": false,
      "id": "24gMLerOZOCIzgxc1+VUtD"
    },
    {
      "folded": false,
      "id": "7885ougj1KuI8Pn4eOychq"
    },
    {
      "folded": false,
      "id": "53oHDhekFF0J1EfC1eesEb"
    },
    {
      "folded": false,
      "id": "ceCozL9x1K3JuWHfQKuRMG"
    },
    {
      "folded": false,
      "id": "40xr+9XbBDpr0T1/CguQyq"
    },
    {
      "folded": false,
      "id": "66tg52wkFOtphDH1KRvRSq"
    },
    {
      "folded": false,
      "id": "aeb4iTe6NOIIjsmWOBjhuO"
    },
    {
      "folded": false,
      "id": "f2CXZIGchAx6hHrmOPBEDH"
    },
    {
      "folded": false,
      "id": "12yiQaXoFC/4kjYVZJdc2S"
    }
  ]
}